relyonai/__init__.py
relyonai/_config.py
relyonai/ai.py
relyonai/explain.py
relyonai/llm.py
relyonai/runtime.py
relyonai/utils.py
relyonai/prompt/README.md
relyonai/prompt/__init__.py
relyonai/prompt/prompt.json
relyonai/prompt/prompt.py
relyonai/prompt/examples/README.md
relyonai/prompt/examples/consts.ipynb
relyonai/prompt/examples/env.ipynb
relyonai/prompt/examples/error_fixing.ipynb
relyonai/prompt/examples/errors.ipynb
relyonai/prompt/examples/exploration.ipynb
relyonai/prompt/examples/filename.txt
relyonai/prompt/examples/files.ipynb
relyonai/prompt/examples/format.ipynb
relyonai/prompt/examples/funcs1.ipynb
relyonai/prompt/examples/funcs2.ipynb
relyonai/prompt/examples/funcs3.ipynb
relyonai/prompt/examples/gpt.ipynb
relyonai/prompt/examples/imports.ipynb
relyonai/prompt/examples/lambdas.ipynb
relyonai/prompt/examples/make_prompt.py
relyonai/prompt/examples/other.txt
relyonai/prompt/examples/plt.ipynb
relyonai/prompt/examples/run_all.sh
relyonai/prompt/examples/session.ipynb
relyonai/prompt/examples/template.ipynb
relyonai/prompt/schemas/NEW_SCHEMA.md
relyonai/prompt/schemas/SCHEMA.md
relyonai/prompt/schemas/SIMPLER_SCHEMA.md
relyonai/prompt/system/default.md
relyonai/prompt/system/gpt4-refined.md
relyonai/prompt/system/gpt4.md
relyonai/prompt/system/simpler.md
relyonai/prompt/system/simpler2.md
relyonai-0.1.2.dist-info/METADATA
relyonai-0.1.2.dist-info/WHEEL
relyonai-0.1.2.dist-info/licenses/LICENSE
relyonai-0.1.2.dist-info/RECORD
